{
  "rounds": 100000000,
  "rules": {
    "game_type": "enhc",
    "soft17": "h17",
    "das": false,
    "double_down": "any_two",
    "surrender": "no_surrender",
    "play_ace_pairs": false,
    "max_splits": 4,
    "decks": 6,
    "penetration_cards": 46
  },
  "ev": -0.04631512999999973,
  "stddev": 0.9378369407996568,
  "winning_distrib": {
    "-1.0": 46399917,
    "+0.0": 11831679,
    "+1.0": 41768404
  },
  "hands": {
    "total": 100000000,
    "won": 41768404,
    "lost": 46399917,
    "push": 11831679,
    "busted": 0,
    "blackjack": 0,
    "doubled": 0,
    "split": 0,
    "insured": 0,
    "surrender": 0
  }
}
