{
  "rounds": 100000000,
  "rules": {
    "game_type": "ahc",
    "soft17": "s17",
    "das": true,
    "bj_pays": 1.5,
    "double_down": "any_two",
    "surrender": "early_surrender",
    "play_ace_pairs": false,
    "max_splits": 4,
    "decks": 6,
    "penetration_cards": 250
  },
  "ev": -0.00898066000000003,
  "stddev": 2.762426988004586,
  "winning_distrib": {
    "-8.0": 4143,
    "-7.0": 47170,
    "-6.0": 300734,
    "-5.0": 1178203,
    "-4.0": 5086690,
    "-3.0": 16735052,
    "-2.0": 22239215,
    "-1.0": 4208339,
    "+0.0": 3450509,
    "+1.0": 5480306,
    "+2.0": 15179363,
    "+3.0": 16895539,
    "+4.0": 6887178,
    "+5.0": 1649151,
    "+6.0": 541716,
    "+7.0": 104576,
    "+8.0": 12116
  },
  "hands": {
    "total": 218602417,
    "won": 99869451,
    "lost": 112257323,
    "push": 6475643,
    "busted": 0,
    "blackjack": 0,
    "doubled": 73859295,
    "split": 218602417,
    "insured": 0,
    "surrender": 0
  }
}
