{
  "rounds": 100000000,
  "rules": {
    "game_type": "ahc",
    "soft17": "s17",
    "das": true,
    "bj_pays": 1.5,
    "double_down": "any_two",
    "surrender": "early_surrender",
    "play_ace_pairs": false,
    "max_splits": 4,
    "decks": 6,
    "penetration_cards": 250
  },
  "ev": 0.18051853000000417,
  "stddev": 2.7195278164205012,
  "winning_distrib": {
    "-8.0": 3046,
    "-7.0": 34973,
    "-6.0": 230180,
    "-5.0": 946579,
    "-4.0": 4417741,
    "-3.0": 15229575,
    "-2.0": 20725753,
    "-1.0": 4712035,
    "+0.0": 3914361,
    "+1.0": 5365208,
    "+2.0": 16846408,
    "+3.0": 18288203,
    "+4.0": 7106011,
    "+5.0": 1580970,
    "+6.0": 496518,
    "+7.0": 91910,
    "+8.0": 10529
  },
  "hands": {
    "total": 216815120,
    "won": 106279031,
    "lost": 103284108,
    "push": 7251981,
    "busted": 0,
    "blackjack": 0,
    "doubled": 72414920,
    "split": 216815120,
    "insured": 0,
    "surrender": 0
  }
}
