{
  "rounds": 100000000,
  "rules": {
    "game_type": "ahc",
    "soft17": "s17",
    "das": true,
    "bj_pays": 1.5,
    "double_down": "any_two",
    "surrender": "early_surrender",
    "play_ace_pairs": false,
    "max_splits": 4,
    "decks": 6,
    "penetration_cards": 250
  },
  "ev": 0.270777640000013,
  "stddev": 2.0370021431431473,
  "winning_distrib": {
    "-8.0": 9,
    "-7.0": 227,
    "-6.0": 7747,
    "-5.0": 124993,
    "-4.0": 1021678,
    "-3.0": 5374450,
    "-2.0": 23446849,
    "-1.0": 9147203,
    "+0.0": 13350477,
    "+1.0": 5046750,
    "+2.0": 31194867,
    "+3.0": 8958547,
    "+4.0": 1973212,
    "+5.0": 322381,
    "+6.0": 29328,
    "+7.0": 1267,
    "+8.0": 15
  },
  "hands": {
    "total": 219039756,
    "won": 112017597,
    "lost": 89519638,
    "push": 17502521,
    "busted": 5315478,
    "blackjack": 0,
    "doubled": 15880517,
    "split": 219039756,
    "insured": 0,
    "surrender": 0
  }
}
