{
  "rounds": 100000000,
  "rules": {
    "game_type": "enhc",
    "soft17": "h17",
    "das": false,
    "double_down": "any_two",
    "surrender": "no_surrender",
    "play_ace_pairs": false,
    "max_splits": 4,
    "decks": 6,
    "penetration_cards": 46
  },
  "ev": -0.1130140899999979,
  "stddev": 0.9727197412016205,
  "winning_distrib": {
    "-1.0": 53598498,
    "+0.0": 4104413,
    "+1.0": 42297089
  },
  "hands": {
    "total": 100000000,
    "won": 42297089,
    "lost": 53598498,
    "push": 4104413,
    "busted": 3845846,
    "blackjack": 0,
    "doubled": 0,
    "split": 0,
    "insured": 0,
    "surrender": 0
  }
}
