{
  "rounds": 100000000,
  "rules": {
    "game_type": "ahc",
    "soft17": "s17",
    "das": true,
    "double_down": "any_two",
    "surrender": "no_surrender",
    "play_ace_pairs": false,
    "max_splits": 4,
    "decks": 6,
    "penetration_cards": 46
  },
  "ev": -0.18509730000000257,
  "stddev": 1.9120613238315547,
  "winning_distrib": {
    "-2.0": 50755426,
    "+0.0": 7744013,
    "+2.0": 41500561
  },
  "hands": {
    "total": 100000000,
    "won": 41500561,
    "lost": 50755426,
    "push": 7744013,
    "busted": 0,
    "blackjack": 0,
    "doubled": 100000000,
    "split": 0,
    "insured": 0,
    "surrender": 0
  }
}
