{
  "rounds": 100000000,
  "rules": {
    "game_type": "enhc",
    "soft17": "s17",
    "das": false,
    "double_down": "any_two",
    "surrender": "no_surrender",
    "play_ace_pairs": false,
    "max_splits": 4,
    "decks": 6,
    "penetration_cards": 46
  },
  "ev": 0.25744845000000754,
  "stddev": 0.9132211637562563,
  "winning_distrib": {
    "-1.0": 32140207,
    "+0.0": 9974741,
    "+1.0": 57885052
  },
  "hands": {
    "total": 100000000,
    "won": 57885052,
    "lost": 32140207,
    "push": 9974741,
    "busted": 21323768,
    "blackjack": 0,
    "doubled": 0,
    "split": 0,
    "insured": 0,
    "surrender": 0
  }
}
