{
  "rounds": 100000000,
  "rules": {
    "game_type": "ahc",
    "soft17": "h17",
    "das": true,
    "double_down": "any_two",
    "surrender": "no_surrender",
    "play_ace_pairs": false,
    "max_splits": 4,
    "decks": 6,
    "penetration_cards": 46
  },
  "ev": 0.07253104000000038,
  "stddev": 2.264918837295329,
  "winning_distrib": {
    "-8.0": 114,
    "-7.0": 3526,
    "-6.0": 48230,
    "-5.0": 358172,
    "-4.0": 1966479,
    "-3.0": 9485038,
    "-2.0": 25310551,
    "-1.0": 8760002,
    "+0.0": 8618160,
    "+1.0": 6019854,
    "+2.0": 23812209,
    "+3.0": 11924929,
    "+4.0": 2955708,
    "+5.0": 615171,
    "+6.0": 110195,
    "+7.0": 11140,
    "+8.0": 522
  },
  "hands": {
    "total": 216662344,
    "won": 99022143,
    "lost": 99358308,
    "push": 18281893,
    "busted": 5584276,
    "blackjack": 0,
    "doubled": 36035596,
    "split": 216662344,
    "insured": 0,
    "surrender": 0
  }
}
