{
  "rounds": 100000000,
  "rules": {
    "game_type": "ahc",
    "soft17": "h17",
    "das": true,
    "double_down": "any_two",
    "surrender": "no_surrender",
    "play_ace_pairs": false,
    "max_splits": 4,
    "decks": 6,
    "penetration_cards": 46
  },
  "ev": 0.4549799100000039,
  "stddev": 2.0792934267993517,
  "winning_distrib": {
    "-8.0": 6,
    "-7.0": 301,
    "-6.0": 8636,
    "-5.0": 119401,
    "-4.0": 921437,
    "-3.0": 5308823,
    "-2.0": 22361383,
    "-1.0": 7944885,
    "+0.0": 10508606,
    "+1.0": 3723774,
    "+2.0": 35704139,
    "+3.0": 10749338,
    "+4.0": 2238177,
    "+5.0": 372388,
    "+6.0": 36865,
    "+7.0": 1797,
    "+8.0": 44
  },
  "hands": {
    "total": 216657276,
    "won": 121244197,
    "lost": 81735860,
    "push": 13677219,
    "busted": 0,
    "blackjack": 0,
    "doubled": 18021255,
    "split": 216657276,
    "insured": 0,
    "surrender": 0
  }
}
