{
  "rounds": 100000000,
  "rules": {
    "game_type": "ahc",
    "soft17": "h17",
    "das": false,
    "double_down": "any_two",
    "surrender": "no_surrender",
    "play_ace_pairs": false,
    "max_splits": 4,
    "decks": 6,
    "penetration_cards": 46
  },
  "ev": 0.11555260000000188,
  "stddev": 1.913748978643103,
  "winning_distrib": {
    "-2.0": 43058529,
    "+0.0": 8105312,
    "+2.0": 48836159
  },
  "hands": {
    "total": 100000000,
    "won": 48836159,
    "lost": 43058529,
    "push": 8105312,
    "busted": 0,
    "blackjack": 0,
    "doubled": 100000000,
    "split": 0,
    "insured": 0,
    "surrender": 0
  }
}
