{
  "rounds": 100000000,
  "rules": {
    "game_type": "enhc",
    "soft17": "s17",
    "das": true,
    "double_down": "any_two",
    "surrender": "no_surrender",
    "play_ace_pairs": false,
    "max_splits": 4,
    "decks": 6,
    "penetration_cards": 46
  },
  "ev": 0.07531243000000074,
  "stddev": 0.9628728977174144,
  "winning_distrib": {
    "-1.0": 42874187,
    "+0.0": 6720383,
    "+1.0": 50405430
  },
  "hands": {
    "total": 100000000,
    "won": 50405430,
    "lost": 42874187,
    "push": 6720383,
    "busted": 0,
    "blackjack": 0,
    "doubled": 0,
    "split": 0,
    "insured": 0,
    "surrender": 0
  }
}
