{
  "rounds": 100000000,
  "rules": {
    "game_type": "ahc",
    "soft17": "s17",
    "das": true,
    "bj_pays": 1.5,
    "double_down": "any_two",
    "surrender": "early_surrender",
    "play_ace_pairs": false,
    "max_splits": 4,
    "decks": 6,
    "penetration_cards": 250
  },
  "ev": -0.034509840000000645,
  "stddev": 1.9815096038644282,
  "winning_distrib": {
    "-8.0": 109,
    "-7.0": 3437,
    "-6.0": 41981,
    "-5.0": 284402,
    "-4.0": 1625206,
    "-3.0": 7591835,
    "-2.0": 19604528,
    "-1.0": 13582247,
    "+0.0": 18099766,
    "+1.0": 11887232,
    "+2.0": 16416882,
    "+3.0": 8387781,
    "+4.0": 2030473,
    "+5.0": 364880,
    "+6.0": 70337,
    "+7.0": 8410,
    "+8.0": 494
  },
  "hands": {
    "total": 218201318,
    "won": 86446544,
    "lost": 95297128,
    "push": 36457646,
    "busted": 39710605,
    "blackjack": 0,
    "doubled": 37848437,
    "split": 218201318,
    "insured": 0,
    "surrender": 0
  }
}
