{
  "rounds": 100000000,
  "rules": {
    "game_type": "ahc",
    "soft17": "s17",
    "das": true,
    "bj_pays": 1.5,
    "double_down": "any_two",
    "surrender": "early_surrender",
    "play_ace_pairs": false,
    "max_splits": 4,
    "decks": 6,
    "penetration_cards": 250
  },
  "ev": -0.1678118100000019,
  "stddev": 0.9672380140275869,
  "winning_distrib": {
    "-1.0": 56576099,
    "+0.0": 3628983,
    "+1.0": 39794918
  },
  "hands": {
    "total": 100000000,
    "won": 39794918,
    "lost": 56576099,
    "push": 3628983,
    "busted": 3203079,
    "blackjack": 0,
    "doubled": 0,
    "split": 0,
    "insured": 0,
    "surrender": 0
  }
}
