{
  "rounds": 100000000,
  "rules": {
    "game_type": "ahc",
    "soft17": "s17",
    "das": true,
    "bj_pays": 1.5,
    "double_down": "any_two",
    "surrender": "early_surrender",
    "play_ace_pairs": false,
    "max_splits": 4,
    "decks": 6,
    "penetration_cards": 250
  },
  "ev": -1.115542359999984,
  "stddev": 1.5986785257215763,
  "winning_distrib": {
    "-2.0": 75391156,
    "+0.0": 4994806,
    "+2.0": 19614038
  },
  "hands": {
    "total": 100000000,
    "won": 19614038,
    "lost": 75391156,
    "push": 4994806,
    "busted": 59571338,
    "blackjack": 0,
    "doubled": 100000000,
    "split": 0,
    "insured": 0,
    "surrender": 0
  }
}
