{
  "rounds": 100000000,
  "rules": {
    "game_type": "ahc",
    "soft17": "s17",
    "das": true,
    "double_down": "any_two",
    "surrender": "no_surrender",
    "play_ace_pairs": false,
    "max_splits": 4,
    "decks": 6,
    "penetration_cards": 46
  },
  "ev": -0.02399276999999977,
  "stddev": 1.9472438303677657,
  "winning_distrib": {
    "-8.0": 102,
    "-7.0": 2417,
    "-6.0": 31337,
    "-5.0": 229577,
    "-4.0": 1425026,
    "-3.0": 7140955,
    "-2.0": 19721342,
    "-1.0": 13844980,
    "+0.0": 18457847,
    "+1.0": 12020400,
    "+2.0": 16734087,
    "+3.0": 8139427,
    "+4.0": 1875323,
    "+5.0": 313260,
    "+6.0": 57267,
    "+7.0": 6275,
    "+8.0": 378
  },
  "hands": {
    "total": 216618881,
    "won": 85178105,
    "lost": 93345099,
    "push": 38095677,
    "busted": 38925524,
    "blackjack": 0,
    "doubled": 36030150,
    "split": 216618881,
    "insured": 0,
    "surrender": 0
  }
}
