{
  "rounds": 100000000,
  "rules": {
    "game_type": "enhc",
    "soft17": "s17",
    "das": false,
    "double_down": "any_two",
    "surrender": "no_surrender",
    "play_ace_pairs": false,
    "max_splits": 4,
    "decks": 6,
    "penetration_cards": 46
  },
  "ev": -0.6142601000000135,
  "stddev": 0.7722692247603746,
  "winning_distrib": {
    "-1.0": 79398766,
    "+0.0": 2628478,
    "+1.0": 17972756
  },
  "hands": {
    "total": 100000000,
    "won": 17972756,
    "lost": 79398766,
    "push": 2628478,
    "busted": 76851600,
    "blackjack": 0,
    "doubled": 0,
    "split": 0,
    "insured": 0,
    "surrender": 0
  }
}
