{
  "rounds": 10000000000,
  "rules": {
    "game_type": "ahc",
    "soft17": "s17",
    "das": true,
    "bj_pays": 1.5,
    "double_down": "any_two",
    "surrender": "no_surrender",
    "play_ace_pairs": false,
    "max_splits": 4,
    "decks": 6,
    "penetration_cards": 296
  },
  "ev": 0.771580960899674,
  "stddev": 1.0542227503665267,
  "winning_distrib": {
    "-6.0": 114,
    "-5.0": 22215,
    "-4.0": 1451020,
    "-3.0": 34264476,
    "-2.0": 314997277,
    "-1.0": 568595350,
    "+0.0": 2733180097,
    "+1.0": 3927578278,
    "+2.0": 2174411625,
    "+3.0": 235443376,
    "+4.0": 9904478,
    "+5.0": 150953,
    "+6.0": 740,
    "+7.0": 1
  },
  "hands": {
    "total": 10000000000,
    "won": 7717178655,
    "lost": 1118769847,
    "push": 1164051498,
    "busted": 0,
    "blackjack": 0,
    "doubled": 0,
    "split": 0,
    "insured": 0,
    "surrender": 0
  }
}
