{
  "rounds": 100000000,
  "rules": {
    "game_type": "ahc",
    "soft17": "s17",
    "das": true,
    "bj_pays": 1.5,
    "double_down": "any_two",
    "surrender": "early_surrender",
    "play_ace_pairs": false,
    "max_splits": 4,
    "decks": 6,
    "penetration_cards": 250
  },
  "ev": -0.6303149999999834,
  "stddev": 1.8469485306546034,
  "winning_distrib": {
    "-2.0": 63364323,
    "+0.0": 4787104,
    "+2.0": 31848573
  },
  "hands": {
    "total": 100000000,
    "won": 31848573,
    "lost": 63364323,
    "push": 4787104,
    "busted": 39999618,
    "blackjack": 0,
    "doubled": 100000000,
    "split": 0,
    "insured": 0,
    "surrender": 0
  }
}
