{
  "rounds": 100000000,
  "rules": {
    "game_type": "enhc",
    "soft17": "s17",
    "das": false,
    "double_down": "any_two",
    "surrender": "no_surrender",
    "play_ace_pairs": false,
    "max_splits": 4,
    "decks": 6,
    "penetration_cards": 46
  },
  "ev": -0.13153044000000147,
  "stddev": 1.9341722210712122,
  "winning_distrib": {
    "-2.0": 50267291,
    "+0.0": 6041940,
    "+2.0": 43690769
  },
  "hands": {
    "total": 100000000,
    "won": 43690769,
    "lost": 50267291,
    "push": 6041940,
    "busted": 0,
    "blackjack": 0,
    "doubled": 100000000,
    "split": 0,
    "insured": 0,
    "surrender": 0
  }
}
