{
  "rounds": 100000000,
  "rules": {
    "game_type": "ahc",
    "soft17": "s17",
    "das": true,
    "bj_pays": 1.5,
    "double_down": "any_two",
    "surrender": "early_surrender",
    "play_ace_pairs": false,
    "max_splits": 4,
    "decks": 6,
    "penetration_cards": 250
  },
  "ev": -0.5468918399999888,
  "stddev": 1.7965643622252645,
  "winning_distrib": {
    "-8.0": 4,
    "-7.0": 307,
    "-6.0": 10915,
    "-5.0": 168137,
    "-4.0": 1339847,
    "-3.0": 7172859,
    "-2.0": 31037586,
    "-1.0": 18114347,
    "+0.0": 14775126,
    "+1.0": 7648027,
    "+2.0": 14585992,
    "+3.0": 4260513,
    "+4.0": 759902,
    "+5.0": 113817,
    "+6.0": 11945,
    "+7.0": 665,
    "+8.0": 11
  },
  "hands": {
    "total": 208738327,
    "won": 65757417,
    "lost": 122101967,
    "push": 20878943,
    "busted": 39345855,
    "blackjack": 0,
    "doubled": 15665843,
    "split": 200737730,
    "insured": 0,
    "surrender": 0
  }
}
