{
  "rounds": 100000000,
  "rules": {
    "game_type": "ahc",
    "soft17": "s17",
    "das": true,
    "bj_pays": 1.5,
    "double_down": "any_two",
    "surrender": "early_surrender",
    "play_ace_pairs": false,
    "max_splits": 4,
    "decks": 6,
    "penetration_cards": 250
  },
  "ev": -0.5102583000000039,
  "stddev": 0.8600212059463836,
  "winning_distrib": {
    "-1.0": 75512915,
    "+1.0": 24487085
  },
  "hands": {
    "total": 100000000,
    "won": 24487085,
    "lost": 75512915,
    "push": 0,
    "busted": 0,
    "blackjack": 0,
    "doubled": 0,
    "split": 0,
    "insured": 0,
    "surrender": 0
  }
}
