{
  "rounds": 100000000,
  "rules": {
    "game_type": "ahc",
    "soft17": "s17",
    "das": true,
    "bj_pays": 1.5,
    "double_down": "any_two",
    "surrender": "early_surrender",
    "play_ace_pairs": false,
    "max_splits": 4,
    "decks": 6,
    "penetration_cards": 250
  },
  "ev": -0.103439010000002,
  "stddev": 2.4944887138319527,
  "winning_distrib": {
    "-8.0": 1257,
    "-7.0": 20108,
    "-6.0": 160987,
    "-5.0": 782662,
    "-4.0": 3589920,
    "-3.0": 13991639,
    "-2.0": 24398376,
    "-1.0": 6694871,
    "+0.0": 7750862,
    "+1.0": 6248186,
    "+2.0": 16538719,
    "+3.0": 13866807,
    "+4.0": 4570865,
    "+5.0": 1057079,
    "+6.0": 279835,
    "+7.0": 44163,
    "+8.0": 3664
  },
  "hands": {
    "total": 218187483,
    "won": 94981699,
    "lost": 113622957,
    "push": 9582827,
    "busted": 7737678,
    "blackjack": 0,
    "doubled": 56762019,
    "split": 218187483,
    "insured": 0,
    "surrender": 0
  }
}
