{
  "rounds": 100000000,
  "rules": {
    "game_type": "ahc",
    "soft17": "h17",
    "das": true,
    "double_down": "any_two",
    "surrender": "no_surrender",
    "play_ace_pairs": false,
    "max_splits": 4,
    "decks": 6,
    "penetration_cards": 46
  },
  "ev": -0.1604969599999981,
  "stddev": 0.9870363395403281,
  "winning_distrib": {
    "-1.0": 58024848,
    "+1.0": 41975152
  },
  "hands": {
    "total": 100000000,
    "won": 41975152,
    "lost": 58024848,
    "push": 0,
    "busted": 0,
    "blackjack": 0,
    "doubled": 0,
    "split": 0,
    "insured": 0,
    "surrender": 0
  }
}
