{
  "rounds": 100000000,
  "rules": {
    "game_type": "ahc",
    "soft17": "s17",
    "das": true,
    "double_down": "any_two",
    "surrender": "no_surrender",
    "play_ace_pairs": false,
    "max_splits": 4,
    "decks": 6,
    "penetration_cards": 46
  },
  "ev": -0.2112658499999983,
  "stddev": 0.9534386292332975,
  "winning_distrib": {
    "-1.0": 58247216,
    "+0.0": 4632153,
    "+1.0": 37120631
  },
  "hands": {
    "total": 100000000,
    "won": 37120631,
    "lost": 58247216,
    "push": 4632153,
    "busted": 30879795,
    "blackjack": 0,
    "doubled": 0,
    "split": 0,
    "insured": 0,
    "surrender": 0
  }
}
