{
  "rounds": 100000000,
  "rules": {
    "game_type": "ahc",
    "soft17": "s17",
    "das": true,
    "bj_pays": 1.5,
    "double_down": "any_two",
    "surrender": "early_surrender",
    "play_ace_pairs": false,
    "max_splits": 4,
    "decks": 6,
    "penetration_cards": 250
  },
  "ev": -0.5465088399999872,
  "stddev": 0.8166299617762623,
  "winning_distrib": {
    "-1.0": 75603262,
    "+0.0": 3444360,
    "+1.0": 20952378
  },
  "hands": {
    "total": 100000000,
    "won": 20952378,
    "lost": 75603262,
    "push": 3444360,
    "busted": 70399994,
    "blackjack": 0,
    "doubled": 0,
    "split": 0,
    "insured": 0,
    "surrender": 0
  }
}
