{
  "rounds": 100000000,
  "rules": {
    "game_type": "enhc",
    "soft17": "s17",
    "das": false,
    "double_down": "any_two",
    "surrender": "no_surrender",
    "play_ace_pairs": false,
    "max_splits": 4,
    "decks": 6,
    "penetration_cards": 46
  },
  "ev": 0.6391554200000046,
  "stddev": 0.6837363335084546,
  "winning_distrib": {
    "-1.0": 11842980,
    "+0.0": 12398498,
    "+1.0": 75758522
  },
  "hands": {
    "total": 100000000,
    "won": 75758522,
    "lost": 11842980,
    "push": 12398498,
    "busted": 0,
    "blackjack": 0,
    "doubled": 0,
    "split": 0,
    "insured": 0,
    "surrender": 0
  }
}
