{
  "rounds": 100000000,
  "rules": {
    "game_type": "ahc",
    "soft17": "s17",
    "das": true,
    "double_down": "any_two",
    "surrender": "no_surrender",
    "play_ace_pairs": false,
    "max_splits": 4,
    "decks": 6,
    "penetration_cards": 46
  },
  "ev": -0.7643537899999955,
  "stddev": 1.7255485282911638,
  "winning_distrib": {
    "-2.0": 60736622,
    "-1.0": 7717741,
    "+0.0": 5167834,
    "+2.0": 26377803
  },
  "hands": {
    "total": 100000000,
    "won": 26377803,
    "lost": 68454363,
    "push": 5167834,
    "busted": 0,
    "blackjack": 0,
    "doubled": 92282259,
    "split": 0,
    "insured": 0,
    "surrender": 0
  }
}
