{
  "rounds": 100000000,
  "rules": {
    "game_type": "ahc",
    "soft17": "h17",
    "das": true,
    "double_down": "any_two",
    "surrender": "no_surrender",
    "play_ace_pairs": false,
    "max_splits": 4,
    "decks": 6,
    "penetration_cards": 46
  },
  "ev": -0.2847795400000034,
  "stddev": 0.9585930433642815,
  "winning_distrib": {
    "-1.0": 64238977,
    "+1.0": 35761023
  },
  "hands": {
    "total": 100000000,
    "won": 35761023,
    "lost": 64238977,
    "push": 0,
    "busted": 0,
    "blackjack": 0,
    "doubled": 0,
    "split": 0,
    "insured": 0,
    "surrender": 0
  }
}
