{
  "rounds": 100000000,
  "rules": {
    "game_type": "ahc",
    "soft17": "s17",
    "das": true,
    "bj_pays": 1.5,
    "double_down": "any_two",
    "surrender": "early_surrender",
    "play_ace_pairs": false,
    "max_splits": 4,
    "decks": 6,
    "penetration_cards": 250
  },
  "ev": 0.2512940299999989,
  "stddev": 0.9246598125993922,
  "winning_distrib": {
    "-1.0": 33342521,
    "+0.0": 8185555,
    "+1.0": 58471924
  },
  "hands": {
    "total": 100000000,
    "won": 58471924,
    "lost": 33342521,
    "push": 8185555,
    "busted": 2468459,
    "blackjack": 0,
    "doubled": 0,
    "split": 0,
    "insured": 0,
    "surrender": 0
  }
}
