{
  "rounds": 100000000,
  "rules": {
    "game_type": "ahc",
    "soft17": "s17",
    "das": true,
    "bj_pays": 1.5,
    "double_down": "any_two",
    "surrender": "early_surrender",
    "play_ace_pairs": false,
    "max_splits": 4,
    "decks": 6,
    "penetration_cards": 250
  },
  "ev": 0.07349679000000173,
  "stddev": 2.372949196288998,
  "winning_distrib": {
    "-8.0": 257,
    "-7.0": 6598,
    "-6.0": 77693,
    "-5.0": 513696,
    "-4.0": 2483239,
    "-3.0": 10662732,
    "-2.0": 25308058,
    "-1.0": 8142277,
    "+0.0": 6486559,
    "+1.0": 5087816,
    "+2.0": 23568655,
    "+3.0": 13011828,
    "+4.0": 3609574,
    "+5.0": 853192,
    "+6.0": 168378,
    "+7.0": 18614,
    "+8.0": 834
  },
  "hands": {
    "total": 219037002,
    "won": 101278077,
    "lost": 101650992,
    "push": 16107933,
    "busted": 0,
    "blackjack": 0,
    "doubled": 39703193,
    "split": 219037002,
    "insured": 0,
    "surrender": 0
  }
}
