{
  "rounds": 100000000,
  "rules": {
    "game_type": "ahc",
    "soft17": "h17",
    "das": false,
    "double_down": "any_two",
    "surrender": "no_surrender",
    "play_ace_pairs": false,
    "max_splits": 4,
    "decks": 6,
    "penetration_cards": 46
  },
  "ev": -0.20226073999999877,
  "stddev": 0.9793317122638026,
  "winning_distrib": {
    "-1.0": 60113037,
    "+1.0": 39886963
  },
  "hands": {
    "total": 100000000,
    "won": 39886963,
    "lost": 60113037,
    "push": 0,
    "busted": 0,
    "blackjack": 0,
    "doubled": 0,
    "split": 0,
    "insured": 0,
    "surrender": 0
  }
}
