{
  "rounds": 100000000,
  "rules": {
    "game_type": "ahc",
    "soft17": "s17",
    "das": true,
    "bj_pays": 1.5,
    "double_down": "any_two",
    "surrender": "early_surrender",
    "play_ace_pairs": false,
    "max_splits": 4,
    "decks": 6,
    "penetration_cards": 250
  },
  "ev": -0.594617110000024,
  "stddev": 1.7826344982281441,
  "winning_distrib": {
    "-2.0": 55880722,
    "-1.0": 8337723,
    "+0.0": 5462827,
    "+2.0": 30318728
  },
  "hands": {
    "total": 100000000,
    "won": 30318728,
    "lost": 64218445,
    "push": 5462827,
    "busted": 0,
    "blackjack": 0,
    "doubled": 91662277,
    "split": 0,
    "insured": 0,
    "surrender": 0
  }
}
