{
  "rounds": 100000000,
  "rules": {
    "game_type": "ahc",
    "soft17": "s17",
    "das": true,
    "bj_pays": 1.5,
    "double_down": "any_two",
    "surrender": "early_surrender",
    "play_ace_pairs": false,
    "max_splits": 4,
    "decks": 6,
    "penetration_cards": 250
  },
  "ev": -0.13315065000000134,
  "stddev": 2.211546694807488,
  "winning_distrib": {
    "-8.0": 269,
    "-7.0": 6365,
    "-6.0": 71952,
    "-5.0": 462023,
    "-4.0": 2318568,
    "-3.0": 10466860,
    "-2.0": 24698622,
    "-1.0": 9341108,
    "+0.0": 13816470,
    "+1.0": 7194523,
    "+2.0": 17612786,
    "+3.0": 10488251,
    "+4.0": 2766926,
    "+5.0": 614034,
    "+6.0": 125581,
    "+7.0": 14831,
    "+8.0": 831
  },
  "hands": {
    "total": 219033478,
    "won": 93083767,
    "lost": 112139660,
    "push": 13810051,
    "busted": 20660514,
    "blackjack": 0,
    "doubled": 39700899,
    "split": 219033478,
    "insured": 0,
    "surrender": 0
  }
}
