{
  "rounds": 100000000,
  "rules": {
    "game_type": "ahc",
    "soft17": "s17",
    "das": true,
    "bj_pays": 1.5,
    "double_down": "any_two",
    "surrender": "early_surrender",
    "play_ace_pairs": false,
    "max_splits": 4,
    "decks": 6,
    "penetration_cards": 250
  },
  "ev": -0.1573109700000011,
  "stddev": 2.7560217823294226,
  "winning_distrib": {
    "-8.0": 4750,
    "-7.0": 52731,
    "-6.0": 334257,
    "-5.0": 1295169,
    "-4.0": 5430820,
    "-3.0": 17590462,
    "-2.0": 23423224,
    "-1.0": 4292132,
    "+0.0": 3407059,
    "+1.0": 5707863,
    "+2.0": 14015881,
    "+3.0": 15712519,
    "+4.0": 6517103,
    "+5.0": 1576895,
    "+6.0": 525195,
    "+7.0": 102106,
    "+8.0": 11834
  },
  "hands": {
    "total": 219030322,
    "won": 93970959,
    "lost": 118400065,
    "push": 6659298,
    "busted": 0,
    "blackjack": 0,
    "doubled": 74429499,
    "split": 219030322,
    "insured": 0,
    "surrender": 0
  }
}
