{
  "rounds": 100000000,
  "rules": {
    "game_type": "ahc",
    "soft17": "s17",
    "das": true,
    "bj_pays": 1.5,
    "double_down": "any_two",
    "surrender": "early_surrender",
    "play_ace_pairs": false,
    "max_splits": 4,
    "decks": 6,
    "penetration_cards": 250
  },
  "ev": 0.231666730000003,
  "stddev": 0.9379134741584128,
  "winning_distrib": {
    "-1.0": 35084221,
    "+0.0": 6664885,
    "+1.0": 58250894
  },
  "hands": {
    "total": 100000000,
    "won": 58250894,
    "lost": 35084221,
    "push": 6664885,
    "busted": 0,
    "blackjack": 0,
    "doubled": 0,
    "split": 0,
    "insured": 0,
    "surrender": 0
  }
}
