{
  "rounds": 100000000,
  "rules": {
    "game_type": "ahc",
    "soft17": "s17",
    "das": true,
    "bj_pays": 1.5,
    "double_down": "any_two",
    "surrender": "early_surrender",
    "play_ace_pairs": false,
    "max_splits": 4,
    "decks": 6,
    "penetration_cards": 250
  },
  "ev": -0.08280505999999874,
  "stddev": 0.9398169454052875,
  "winning_distrib": {
    "-1.0": 48645881,
    "+0.0": 10988744,
    "+1.0": 40365375
  },
  "hands": {
    "total": 100000000,
    "won": 40365375,
    "lost": 48645881,
    "push": 10988744,
    "busted": 24861549,
    "blackjack": 0,
    "doubled": 0,
    "split": 0,
    "insured": 0,
    "surrender": 0
  }
}
