{
  "rounds": 100000000,
  "rules": {
    "game_type": "enhc",
    "soft17": "s17",
    "das": false,
    "double_down": "any_two",
    "surrender": "no_surrender",
    "play_ace_pairs": false,
    "max_splits": 4,
    "decks": 6,
    "penetration_cards": 46
  },
  "ev": -1.0295419600000022,
  "stddev": 1.64968715210312,
  "winning_distrib": {
    "-2.0": 73006353,
    "+0.0": 5464392,
    "+2.0": 21529255
  },
  "hands": {
    "total": 100000000,
    "won": 21529255,
    "lost": 73006353,
    "push": 5464392,
    "busted": 46305264,
    "blackjack": 0,
    "doubled": 100000000,
    "split": 0,
    "insured": 0,
    "surrender": 0
  }
}
